{
  "basic": {
    "name": "ソニーグループ株式会社",
    "name_en": "SONY GROUP CORPORATION",
    "name_ko": "소니그룹",
    "headquarters": "東京都港区港南１丁目７番１号",
    "headquarters_en": "",
    "headquarters_ko": "도쿄도 미나토구 고난 1가 7번 1호",
    "founded_year": 1946,
    "industry": "",
    "market_cap": 26573332000000,
    "sec_code": "6758",
    "employee_count": 112300
  },
  "hr": {
    "avgTenureYears": 15.8,
    "avgAgeYears": 42.5,
    "avgAnnualSalaryJPY": 11183744
  },
  "financials": {
    "revenueJPY": null,
    "fiscalYear": 2025
  },
  "philosophy": {
    "mission": "",
    "vision": "",
    "values": []
  },
  "provenance": {
    "source": "EDINET API v2",
    "document_id": "S100W19Q",
    "submitted_date": "2025-06-20",
    "fetched_at": "2025-09-21T20:30:27.022887",
    "company_key": "sony",
    "employee_info_provenance": {
      "avgTenureYears": {
        "file": "XBRL/PublicDoc/0101010_honbun_jpcrp030000-asr-001_E01777-000_2025-03-31_01_2025-06-20_ixbrl.htm",
        "concept": "jpcrp_cor:AverageLengthOfServiceYearsInformationAboutReportingCompanyInformationAboutEmployees",
        "contextRef": "CurrentYearInstant_NonConsolidatedMember",
        "unitRef": "pure",
        "scale": "0",
        "method": "ixbrl_concept"
      },
      "avgAgeYears": {
        "file": "XBRL/PublicDoc/0101010_honbun_jpcrp030000-asr-001_E01777-000_2025-03-31_01_2025-06-20_ixbrl.htm",
        "concept": "jpcrp_cor:AverageAgeYearsInformationAboutReportingCompanyInformationAboutEmployees",
        "contextRef": "CurrentYearInstant_NonConsolidatedMember",
        "unitRef": "pure",
        "scale": "0",
        "method": "ixbrl_concept"
      },
      "avgAnnualSalaryJPY": {
        "file": "XBRL/PublicDoc/0101010_honbun_jpcrp030000-asr-001_E01777-000_2025-03-31_01_2025-06-20_ixbrl.htm",
        "concept": "jpcrp_cor:AverageAnnualSalaryInformationAboutReportingCompanyInformationAboutEmployees",
        "contextRef": "CurrentYearInstant_NonConsolidatedMember",
        "unitRef": "JPY",
        "scale": "0",
        "method": "ixbrl_concept"
      },
      "employeeCount": {
        "file": "XBRL/PublicDoc/0101010_honbun_jpcrp030000-asr-001_E01777-000_2025-03-31_01_2025-06-20_ixbrl.htm",
        "concept": "jpcrp_cor:NumberOfEmployees",
        "contextRef": "CurrentYearInstant",
        "unitRef": "pure",
        "scale": "0",
        "method": "ixbrl_concept"
      }
    }
  }
}